{
  "coc.source.around.enable": false,
  "coc.source.buffer.enable": false,
  "coc.source.file.enable": false,
  "coc.source.file.disableSyntaxes": ["string"],
  "css.validate": false,
  "diagnostic.refreshOnInsertMode": false,
  "explorer.icon.enableNerdfont": true,
  "explorer.file.autoReveal": true,
  "explorer.quitOnOpen": true,
  "explorer.width": 50,
  "explorer.toggle": true,
  "eslint.autoFixOnSave": true,
  "eslint.packageManager": "yarn",
  "javascript.suggestionActions.enabled": true,
  "json.format.enable": true,
  "languageserver": {
    "ocaml-lsp": {
      "command": "opam",
      "args": ["config", "exec", "--", "ocamllsp"],
      "filetypes": ["ocaml", "reason"]
    }
  },
  "scss.validate": false,
  "stylelintplus.autoFixOnSave": true,
  "suggest.snippetIndicator": " ",
  "suggest.noselect": true,
  "suggest.triggerAfterInsertEnter": true,
  "tsserver.enable": true,
  "tsserver.log": "verbose",
  "tsserver.npm": "/home/chuck/.nvm/versions/node/v10.15.0/bin/npm",
  "tsserver.trace.server": "verbose",
  "typescript.preferences.quoteStyle": "single",
  "typescript.suggest.autoImports": true,
  "vetur.experimental.templateInterpolationService": false,
  "vetur.ignoreProjectWarning": true,
  "wxss.validate": false
}
